vip_ivp/__init__.py
vip_ivp/api.py
vip_ivp/base.py
vip_ivp/solver_utils.py
vip_ivp/utils.py
vip_ivp-0.2.0.dist-info/licenses/LICENSE
vip_ivp-0.2.0.dist-info/METADATA
vip_ivp-0.2.0.dist-info/WHEEL
vip_ivp-0.2.0.dist-info/top_level.txt
vip_ivp-0.2.0.dist-info/RECORD
