Metadata-Version: 2.4
Name: vip_ivp
Version: 0.2.0
Summary: Solve ODEs without having to build the system of equations.
Home-page: https://github.com/ngripon/vip-ivp
Author: Nathan Gripon
Author-email: n.gripon@gmail.com
Project-URL: Bug Tracker, https://github.com/ngripon/vip-ivp/issues
Classifier: Programming Language :: Python :: 3
Classifier: License :: OSI Approved :: MIT License
Classifier: Operating System :: OS Independent
Requires-Python: >=3.9
License-File: LICENSE
Requires-Dist: numpy
Requires-Dist: scipy
Requires-Dist: matplotlib
Requires-Dist: pandas
Requires-Dist: cachebox
Requires-Dist: typing_extensions
Dynamic: author
Dynamic: author-email
Dynamic: classifier
Dynamic: description
Dynamic: description-content-type
Dynamic: home-page
Dynamic: license-file
Dynamic: project-url
Dynamic: requires-dist
Dynamic: requires-python
Dynamic: summary
